os_ios_prepare_ipa_file
