Metadata-Version: 1.1
Name: os-ios-prepare-ipa-file
Version: 2.6
Summary: Will prepare an .ipa file for distribution in an HTTPS server
Home-page: https://github.com/osfunapps/os-ios-prepare-ipa-file-py
Author: Oz Shabat
Author-email: support@os-apps.com
License: MIT
Keywords: python,osfunapps,osapps,files,xml,tools,utils,ios,automation
Platform: UNKNOWN
Classifier: Development Status :: 5 - Production/Stable
Classifier: Intended Audience :: Developers
Classifier: Topic :: Software Development :: Build Tools
Classifier: License :: OSI Approved :: MIT License
Classifier: Programming Language :: Python :: 3
Classifier: Programming Language :: Python :: 3.4
Classifier: Programming Language :: Python :: 3.5
Classifier: Programming Language :: Python :: 3.6
Classifier: Programming Language :: Python :: 3.9
